requirements.txt
setup.py
django_passwordless_user/__init__.py
django_passwordless_user/models.py
django_passwordless_user.egg-info/PKG-INFO
django_passwordless_user.egg-info/SOURCES.txt
django_passwordless_user.egg-info/dependency_links.txt
django_passwordless_user.egg-info/requires.txt
django_passwordless_user.egg-info/top_level.txt