Metadata-Version: 2.1
Name: django-passwordless-user
Version: 2020.7.1
Summary: Django User model without password field
Home-page: https://github.com/andrewp-as-is/django-passwordless-user.py
License: Unlicense
Keywords: django passwordless user
Platform: UNKNOWN
Classifier: Framework :: Django
Classifier: License :: Public Domain
Classifier: Operating System :: OS Independent
Classifier: Programming Language :: Python :: 3
